facturacion_electronica/__init__.py
facturacion_electronica/_version.py
facturacion_electronica/caf.py
facturacion_electronica/cedente.py
facturacion_electronica/cesion.py
facturacion_electronica/cesion_imagen.py
facturacion_electronica/cesionario.py
facturacion_electronica/clase_util.py
facturacion_electronica/conexion.py
facturacion_electronica/consumo_folios.py
facturacion_electronica/documento.py
facturacion_electronica/documento_comisiones.py
facturacion_electronica/documento_exportacion.py
facturacion_electronica/documento_linea.py
facturacion_electronica/documento_linea_cdg_item.py
facturacion_electronica/documento_referencias.py
facturacion_electronica/documento_respuesta.py
facturacion_electronica/dte.py
facturacion_electronica/emisor.py
facturacion_electronica/envio.py
facturacion_electronica/facturacion_electronica.py
facturacion_electronica/firma.py
facturacion_electronica/global_descuento_recargo.py
facturacion_electronica/impuestos.py
facturacion_electronica/libro.py
facturacion_electronica/libro_boletas.py
facturacion_electronica/linea_impuesto.py
facturacion_electronica/receptor.py
facturacion_electronica/respuesta.py
facturacion_electronica/signature_cert.py
facturacion_electronica/xsd/AEC_v10.xsd
facturacion_electronica/xsd/Cesion_v10.xsd
facturacion_electronica/xsd/ConsumoFolio_v10.xsd
facturacion_electronica/xsd/DTECedido_v10.xsd
facturacion_electronica/xsd/DTE_v10.xsd
facturacion_electronica/xsd/EnvioBOLETA_v11.xsd
facturacion_electronica/xsd/EnvioDTE_v10.xsd
facturacion_electronica/xsd/EnvioRecibos_v10.xsd
facturacion_electronica/xsd/LceCal_v10.xsd
facturacion_electronica/xsd/LceCoCertif_v10.xsd
facturacion_electronica/xsd/LceSiiTypes_v10.xsd
facturacion_electronica/xsd/LibroBOLETA_v10.xsd
facturacion_electronica/xsd/LibroCVS_v10.xsd
facturacion_electronica/xsd/LibroCV_v10.xsd
facturacion_electronica/xsd/LibroGuia_v10.xsd
facturacion_electronica/xsd/Recibos_v10.xsd
facturacion_electronica/xsd/RespSII_v10.xsd
facturacion_electronica-0.20.3.dist-info/LICENSE
facturacion_electronica-0.20.3.dist-info/METADATA
facturacion_electronica-0.20.3.dist-info/WHEEL
facturacion_electronica-0.20.3.dist-info/top_level.txt
facturacion_electronica-0.20.3.dist-info/RECORD
