Metadata-Version: 2.1
Name: facturacion-electronica
Version: 0.20.3
Home-page: https://gitlab.com/dansanti/facturacion_electronica
Author: Daniel Santibáñez Polanco
Author-email: dansanti@gmail.com
License: GPLV3+
Classifier: Development Status :: 4 - Beta
Classifier: License :: OSI Approved :: GNU General Public License v3 or later (GPLv3+)
Classifier: Programming Language :: Python :: 3.6
Classifier: Intended Audience :: Developers
Classifier: Topic :: Software Development :: Libraries :: Python Modules
Classifier: Environment :: Console
License-File: LICENSE
Requires-Dist: certifi
Requires-Dist: cryptography ==41.0.7
Requires-Dist: lxml
Requires-Dist: pdf417gen >=0.6.0
Requires-Dist: pyOpenSSL ==23.2.0
Requires-Dist: pytz
Requires-Dist: requests >=2.24.0
Requires-Dist: urllib3
Requires-Dist: zeep >=3.4.0
